odoo/addons/purchase_discount/README.rst
odoo/addons/purchase_discount/__init__.py
odoo/addons/purchase_discount/__manifest__.py
odoo/addons/purchase_discount/i18n/de.po
odoo/addons/purchase_discount/i18n/el_GR.po
odoo/addons/purchase_discount/i18n/es.po
odoo/addons/purchase_discount/i18n/es_DO.po
odoo/addons/purchase_discount/i18n/es_MX.po
odoo/addons/purchase_discount/i18n/fr.po
odoo/addons/purchase_discount/i18n/fr_CH.po
odoo/addons/purchase_discount/i18n/hr.po
odoo/addons/purchase_discount/i18n/it.po
odoo/addons/purchase_discount/i18n/nl.po
odoo/addons/purchase_discount/i18n/pt_BR.po
odoo/addons/purchase_discount/i18n/pt_PT.po
odoo/addons/purchase_discount/i18n/purchase_discount.pot
odoo/addons/purchase_discount/i18n/sl.po
odoo/addons/purchase_discount/i18n/zh_CN.po
odoo/addons/purchase_discount/images/purchase_discount.png
odoo/addons/purchase_discount/models/__init__.py
odoo/addons/purchase_discount/models/product_supplierinfo.py
odoo/addons/purchase_discount/models/purchase_order.py
odoo/addons/purchase_discount/models/res_partner.py
odoo/addons/purchase_discount/models/stock_move.py
odoo/addons/purchase_discount/models/stock_rule.py
odoo/addons/purchase_discount/readme/CONTRIBUTORS.rst
odoo/addons/purchase_discount/readme/DESCRIPTION.rst
odoo/addons/purchase_discount/readme/ROADMAP.rst
odoo/addons/purchase_discount/readme/USAGE.rst
odoo/addons/purchase_discount/report/__init__.py
odoo/addons/purchase_discount/report/purchase_report.py
odoo/addons/purchase_discount/static/description/icon.png
odoo/addons/purchase_discount/static/description/icon.svg
odoo/addons/purchase_discount/static/description/index.html
odoo/addons/purchase_discount/static/description/product_supplierinfo_form.png
odoo/addons/purchase_discount/static/description/res_partner_company_form.png
odoo/addons/purchase_discount/static/description/res_partner_individual_form.png
odoo/addons/purchase_discount/tests/__init__.py
odoo13_addon_purchase_discount-13.0.1.1.2.dist-info/METADATA
odoo13_addon_purchase_discount-13.0.1.1.2.dist-info/WHEEL
odoo13_addon_purchase_discount-13.0.1.1.2.dist-info/top_level.txt
odoo13_addon_purchase_discount-13.0.1.1.2.dist-info/RECORD
